ctc/__init__.py
ctc/__main__.py
ctc/py.typed
ctc/cli/__init__.py
ctc/cli/cli_run.py
ctc/cli/cli_utils/__init__.py
ctc/cli/cli_utils/cli_alias_utils.py
ctc/cli/cli_utils/cli_charset_utils.py
ctc/cli/cli_utils/cli_color_utils.py
ctc/cli/cli_utils/cli_execution_utils.py
ctc/cli/cli_utils/cli_output_utils.py
ctc/cli/cli_utils/cli_parse_utils.py
ctc/cli/commands/__init__.py
ctc/cli/commands/root_command.py
ctc/cli/commands/admin/__init__.py
ctc/cli/commands/admin/aliases_command.py
ctc/cli/commands/admin/chains_command.py
ctc/cli/commands/admin/charset_command.py
ctc/cli/commands/admin/color_command.py
ctc/cli/commands/admin/config_command.py
ctc/cli/commands/admin/log_command.py
ctc/cli/commands/admin/setup_command.py
ctc/cli/commands/admin/config/__init__.py
ctc/cli/commands/admin/config/edit_command.py
ctc/cli/commands/admin/config/path_command.py
ctc/cli/commands/admin/db/__init__.py
ctc/cli/commands/admin/db/create_tables_command.py
ctc/cli/commands/admin/db/drop_command.py
ctc/cli/commands/admin/db/login_command.py
ctc/cli/commands/admin/db/status_command.py
ctc/cli/commands/compute/__init__.py
ctc/cli/commands/compute/ascii_command.py
ctc/cli/commands/compute/checksum_command.py
ctc/cli/commands/compute/create_address_command.py
ctc/cli/commands/compute/decode_call_command.py
ctc/cli/commands/compute/decode_command.py
ctc/cli/commands/compute/encode_command.py
ctc/cli/commands/compute/hex_command.py
ctc/cli/commands/compute/integer_command.py
ctc/cli/commands/compute/keccak_command.py
ctc/cli/commands/compute/limits_command.py
ctc/cli/commands/compute/lower_command.py
ctc/cli/commands/compute/rlp_encode.py
ctc/cli/commands/compute/selector_command.py
ctc/cli/commands/data/__init__.py
ctc/cli/commands/data/abi_command.py
ctc/cli/commands/data/abi_diff_command.py
ctc/cli/commands/data/address_command.py
ctc/cli/commands/data/address_txs_command.py
ctc/cli/commands/data/block_command.py
ctc/cli/commands/data/blocks_command.py
checkthechain-0.3.9.dist-info/entry_points.txt
checkthechain-0.3.9.dist-info/LICENSE-APACHE
checkthechain-0.3.9.dist-info/LICENSE-MIT
checkthechain-0.3.9.dist-info/WHEEL
checkthechain-0.3.9.dist-info/METADATA
checkthechain-0.3.9.dist-info/RECORD
