Metadata-Version: 2.1
Name: checkthechain
Version: 0.3.9
Summary: ctc is a tool for collecting and processing historical EVM data
Requires-Python: >=3.7
Classifier: Development Status :: 4 - Beta
Classifier: Intended Audience :: Developers
Classifier: Intended Audience :: Financial and Insurance Industry
Classifier: Intended Audience :: Science/Research
Classifier: License :: OSI Approved :: Apache Software License
Classifier: License :: OSI Approved :: MIT License
Classifier: Natural Language :: English
Classifier: Operating System :: MacOS
Classifier: Operating System :: Microsoft :: Windows
Classifier: Operating System :: POSIX :: Linux
Classifier: Programming Language :: Python :: 3.7
Classifier: Programming Language :: Python :: 3.8
Classifier: Programming Language :: Python :: 3.9
Classifier: Programming Language :: Python :: 3.10
Classifier: Programming Language :: Python :: 3.11
Classifier: Typing :: Typed
Requires-Dist: typing-extensions >=4.2.0, <5
Requires-Dist: numpy >=1.19.0, <1.24
Requires-Dist: polars >=0.17.3, <0.18
Requires-Dist: pyarrow >=12.0.0, <13
Requires-Dist: aiohttp >=3.7.4, <4
Requires-Dist: loguru >=0.5.3, <0.7
Requires-Dist: msgspec >=0.14.1, <0.15
Requires-Dist: orjson >=3.7.9, <4
Requires-Dist: requests >=2.20.0, <3
Requires-Dist: toml >=0.10.2, <0.11
Requires-Dist: toolcli >=0.6.13, <0.7
Requires-Dist: toolconf >=0.1.2, <0.2
Requires-Dist: toolsql >=0.6.1, <0.7
Requires-Dist: toolstr >=0.9.3, <0.10
Requires-Dist: tooltime >=0.2.10, <0.3
Requires-Dist: pycryptodome >=3.9.1, <4
Requires-Dist: eth_abi_lite >=3.2.0, <4
Requires-Dist: idna >=2.10, <4
Requires-Dist: mypy ==1.2.0 ; extra == "test"
Requires-Dist: mypy_extensions >= 1.0.0, <1.1.0 ; extra == "test"
Requires-Dist: pytest-asyncio ==0.18.0 ; extra == "test"
Requires-Dist: pytest-xdist ==3.1.0 ; extra == "test"
Requires-Dist: pytest >=6 ; extra == "test"
Requires-Dist: tox-asdf ==0.1.0 ; extra == "test"
Requires-Dist: tox ==3.8.0 ; extra == "test"
Requires-Dist: virtualenv >=20.6.0 ; extra == "test"
Requires-Dist: types-requests >= 2.28.11.17 ; extra == "test"
Project-URL: Documentation, https://ctc.readthedocs.io/en/latest/
Project-URL: Source, https://github.com/fei-protocol/checkthechain
Provides-Extra: test
